cognee_integration_openai_agents/__init__.py
cognee_integration_openai_agents/bootstrap.py
cognee_integration_openai_agents/tools.py
cognee_integration_openai_agents-0.1.0.dist-info/METADATA
cognee_integration_openai_agents-0.1.0.dist-info/WHEEL
cognee_integration_openai_agents-0.1.0.dist-info/top_level.txt
cognee_integration_openai_agents-0.1.0.dist-info/RECORD
