Metadata-Version: 2.4
Name: cognee-integration-openai-agents
Version: 0.1.0
Summary: Integrate Cognee's memory seamlessly with your OpenAI Agents SDK using easy-to-use tools.
Requires-Python: >=3.10
Requires-Dist: cognee>=0.5.0
Requires-Dist: openai-agents>=0.0.1
Requires-Dist: python-dotenv>=1.0.0
Requires-Dist: ruff>=0.14.9
